mlprimitives/__init__.py
mlprimitives/cli.py
mlprimitives/datasets.py
mlprimitives/evaluation.py
mlprimitives/utils.py
mlprimitives/adapters/__init__.py
mlprimitives/adapters/community.py
mlprimitives/adapters/cv2.py
mlprimitives/adapters/featuretools.py
mlprimitives/adapters/keras.py
mlprimitives/adapters/lightfm.py
mlprimitives/adapters/networkx.py
mlprimitives/adapters/pandas.py
mlprimitives/adapters/skimage.py
mlprimitives/adapters/statsmodels.py
mlprimitives/candidates/__init__.py
mlprimitives/candidates/audio_featurization.py
mlprimitives/candidates/audio_padding.py
mlprimitives/candidates/dsp.py
mlprimitives/candidates/timeseries/__init__.py
mlprimitives/candidates/timeseries/cyclegan.py
mlprimitives/custom/__init__.py
mlprimitives/custom/counters.py
mlprimitives/custom/feature_extraction.py
mlprimitives/custom/feature_selection.py
mlprimitives/custom/preprocessing.py
mlprimitives/custom/text.py
mlprimitives/custom/timeseries_anomalies.py
mlprimitives/custom/timeseries_preprocessing.py
mlprimitives/custom/trivial.py
mlprimitives/pipelines/graph.graph_matching.nx.xgb.json
mlprimitives/pipelines/graph.link_prediction.nx.xgb.json
mlprimitives/pipelines/image.classification.hog.rf.json
mlprimitives/pipelines/image.classification.hog.xgb.json
mlprimitives/pipelines/image.classification.resnet50.xgb.json
mlprimitives/pipelines/image.regression.hog.rf.json
mlprimitives/pipelines/image.regression.hog.xgb.json
mlprimitives/pipelines/image.regression.resnet50.xgb.json
mlprimitives/pipelines/keras.Sequential.LSTMBinaryTextClassifier.json
mlprimitives/pipelines/keras.Sequential.LSTMTextClassifier.json
mlprimitives/pipelines/keras.Sequential.MLPBinaryClassifier.json
mlprimitives/pipelines/keras.Sequential.MLPMultiClassClassifier.json
mlprimitives/pipelines/keras.Sequential.SingleLayerCNNImageClassifier.json
mlprimitives/pipelines/keras.Sequential.SingleLayerCNNImageRegressor.json
mlprimitives/pipelines/keras.Sequential.VGGCNNClassifier.json
mlprimitives-0.4.1.dist-info/AUTHORS.rst
mlprimitives-0.4.1.dist-info/LICENSE
mlprimitives-0.4.1.dist-info/METADATA
mlprimitives-0.4.1.dist-info/WHEEL
mlprimitives-0.4.1.dist-info/entry_points.txt
mlprimitives-0.4.1.dist-info/top_level.txt
mlprimitives-0.4.1.dist-info/RECORD
