Metadata-Version: 2.1
Name: mlprimitives
Version: 0.4.1
Summary: Pipelines and primitives for machine learning and data science.
Home-page: https://github.com/MLBazaar/MLPrimitives
Author: MIT Data To AI Lab
Author-email: dailabmit@gmail.com
License: MIT license
Keywords: mlblocks mlprimitives pipelines primitives machine learning data science
Classifier: Development Status :: 2 - Pre-Alpha
Classifier: Intended Audience :: Developers
Classifier: License :: OSI Approved :: MIT License
Classifier: Natural Language :: English
Classifier: Programming Language :: Python :: 3
Classifier: Programming Language :: Python :: 3.8
Classifier: Programming Language :: Python :: 3.9
Classifier: Programming Language :: Python :: 3.10
Classifier: Programming Language :: Python :: 3.11
Requires-Python: >=3.8,<3.12
License-File: LICENSE
License-File: AUTHORS.rst
Requires-Dist: Keras<2.15,>=2.4
Requires-Dist: featuretools<0.23,>=0.6.1
Requires-Dist: iso639<0.2,>=0.1.4
Requires-Dist: langdetect<2,>=1.0.7
Requires-Dist: lightfm<2,>=1.15
Requires-Dist: mlblocks<0.7,>=0.6
Requires-Dist: networkx<3,>=2.0
Requires-Dist: nltk<4,>=3.3
Requires-Dist: numpy<2,>=1.16.0
Requires-Dist: opencv-python<4.7,>=3.4.0.12
Requires-Dist: pandas<2,>=1
Requires-Dist: python-louvain<0.14,>=0.10
Requires-Dist: scikit-image>=0.15
Requires-Dist: scikit-learn>=0.21
Requires-Dist: scipy<2,>=1.1.0
Requires-Dist: statsmodels<0.15,>=0.9.0
Requires-Dist: tensorflow<2.15,>=2
Requires-Dist: xgboost<2,>=0.72.1
Requires-Dist: protobuf<4
Provides-Extra: dev
Requires-Dist: pytest>=3.4.2; extra == "dev"
Requires-Dist: pytest-cov>=2.6.0; extra == "dev"
Requires-Dist: rundoc<0.5,>=0.4.3; extra == "dev"
Requires-Dist: bumpversion<0.6,>=0.5.3; extra == "dev"
Requires-Dist: pip>=9.0.1; extra == "dev"
Requires-Dist: watchdog<0.11,>=0.8.3; extra == "dev"
Requires-Dist: m2r<0.3,>=0.2.0; extra == "dev"
Requires-Dist: Sphinx<3,>=1.7.1; extra == "dev"
Requires-Dist: sphinx-rtd-theme<0.5,>=0.2.4; extra == "dev"
Requires-Dist: docutils<0.18,>=0.14; extra == "dev"
Requires-Dist: ipython>=6.5.0; extra == "dev"
Requires-Dist: mistune<2,>=0.7; extra == "dev"
Requires-Dist: Jinja2<3.1,>=2; extra == "dev"
Requires-Dist: alabaster<=0.7.12; extra == "dev"
Requires-Dist: sphinxcontrib-applehelp<1.0.8; extra == "dev"
Requires-Dist: sphinxcontrib-devhelp<1.0.6; extra == "dev"
Requires-Dist: sphinxcontrib-htmlhelp<2.0.5; extra == "dev"
Requires-Dist: sphinxcontrib-serializinghtml<1.1.10; extra == "dev"
Requires-Dist: sphinxcontrib-qthelp<1.0.7; extra == "dev"
Requires-Dist: flake8<4,>=3.7.7; extra == "dev"
Requires-Dist: isort<5,>=4.3.4; extra == "dev"
Requires-Dist: autoflake<2,>=1.1; extra == "dev"
Requires-Dist: autopep8<2,>=1.4.3; extra == "dev"
Requires-Dist: importlib-metadata<5; extra == "dev"
Requires-Dist: twine<4,>=1.10.0; extra == "dev"
Requires-Dist: wheel>=0.30.0; extra == "dev"
Requires-Dist: coverage<6,>=4.5.1; extra == "dev"
Requires-Dist: tox<4,>=2.9.1; extra == "dev"
Provides-Extra: test
Requires-Dist: pytest>=3.4.2; extra == "test"
Requires-Dist: pytest-cov>=2.6.0; extra == "test"
Requires-Dist: rundoc<0.5,>=0.4.3; extra == "test"
